pytest_rest_api/__init__.py
pytest_rest_api/clients.py
pytest_rest_api/fixtures.py
pytest_rest_api/logger.py
pytest_rest_api/plugin.py
pytest_rest_api/requests.py
pytest_rest_api/responses.py
pytest_rest_api-0.1.0.dist-info/WHEEL
pytest_rest_api-0.1.0.dist-info/METADATA
pytest_rest_api-0.1.0.dist-info/RECORD
