Metadata-Version: 2.1
Name: pytest-rest-api
Version: 0.1.0
Summary: 
Author: rocshers
Author-email: prog.rocshers@gmail.com
Requires-Python: >=3.10,<4.0
Classifier: Programming Language :: Python :: 3
Classifier: Programming Language :: Python :: 3.10
Requires-Dist: pytest (>=7.1.2,<8.0.0)
Requires-Dist: requests (>=2.27.1,<3.0.0)
